{
    "center":  [
                   31.2135,
                   121.44375
               ],
    "candidates":  [
                       {
                           "name":  "æå·´å\u0085åå¡",
                           "addr":  "ä¸æµ·å¸å¾æ±åºæ·®æµ·ä¸­è·¯1000å·",
                           "lat":  31.215,
                           "lon":  121.445,
                           "avg_travel_time_min":  12.5,
                           "raw":  null
                       },
                       {
                           "name":  "çå¹¸åå¡",
                           "addr":  "ä¸æµ·å¸å¾æ±åºå®å±±è·¯900å·",
                           "lat":  31.218,
                           "lon":  121.443,
                           "avg_travel_time_min":  15.3,
                           "raw":  null
                       },
                       {
                           "name":  "COSTAåå¡",
                           "addr":  "ä¸æµ·å¸å¾æ±åºåå±±è·¯888å·",
                           "lat":  31.213,
                           "lon":  121.446,
                           "avg_travel_time_min":  14.7,
                           "raw":  null
                       }
                   ],
    "note":  "ç¾åº¦APIè°ç¨å¤±è´¥: APP Refereræ ¡éªå¤±è´¥ãè¿åæ¨¡ææ°æ®ç¨äºæ¼ç¤ºã"
}
